MANIFEST.in
README.rst
setup.py
rigcollector/__init__.py
rigcollector/app.py
rigcollector/collector.py
rigcollector.egg-info/PKG-INFO
rigcollector.egg-info/SOURCES.txt
rigcollector.egg-info/dependency_links.txt
rigcollector.egg-info/entry_points.txt
rigcollector.egg-info/not-zip-safe
rigcollector.egg-info/requires.txt
rigcollector.egg-info/top_level.txt
rigcollector/custom/__init__.py
rigcollector/custom/dummy.py
rigcollector/custom/linux.py
rigcollector/custom/mtgox.py
rigcollector/custom/slushspool.py
rigcollector/custom/windows.py