Metadata-Version: 1.1
Name: rigcollector
Version: 0.1.0
Summary: Collector for rigsmonitoring.com
Home-page: https://github.com/RigsMonitoring/rigcollector
Author: Thomas Sileo
Author-email: thomas.sileo@gmail.com
License: MIT
Keywords: monitoring metrics system
Platform: UNKNOWN
Classifier: Development Status :: 4 - Beta
Classifier: Intended Audience :: Developers
Classifier: License :: OSI Approved :: MIT License
Classifier: Programming Language :: Python
